LICENSE
README.md
setup.cfg
setup.py
sentenai/__init__.py
sentenai/api.py
sentenai/new.py
sentenai.egg-info/PKG-INFO
sentenai.egg-info/SOURCES.txt
sentenai.egg-info/dependency_links.txt
sentenai.egg-info/requires.txt
sentenai.egg-info/top_level.txt
sentenai/stream/__init__.py
sentenai/stream/events.py
sentenai/stream/metadata.py
sentenai/stream/streams.py
tests/test_api.py
tests/test_utils.py