Metadata-Version: 2.2
Name: sentenai
Version: 1.7.2.4
Summary: Client library for Sentenai
Home-page: https://github.com/sentenai/py-sentenai
Author: Sentenai, Inc.
Author-email: info@sentenai.com
License: BSD
Keywords: sentenai cloud sensor database
Classifier: Development Status :: 4 - Beta
Classifier: Intended Audience :: Developers
Classifier: Topic :: Database
Classifier: License :: OSI Approved :: BSD License
Classifier: Programming Language :: Python :: 3.7
Classifier: Programming Language :: Python :: 3.8
Classifier: Programming Language :: Python :: 3.9
Classifier: Programming Language :: Python :: 3.10
Classifier: Programming Language :: Python :: 3.11
Classifier: Programming Language :: Python :: 3.12
License-File: LICENSE
Requires-Dist: dateutils
Requires-Dist: pytz
Requires-Dist: requests
Requires-Dist: shapely
Requires-Dist: simplejson
Requires-Dist: numpy
Requires-Dist: treelib
Requires-Dist: tqdm
Requires-Dist: cbor2
Dynamic: author
Dynamic: author-email
Dynamic: classifier
Dynamic: home-page
Dynamic: keywords
Dynamic: license
Dynamic: requires-dist
Dynamic: summary
